[
  {
    "id": "interview-cake-0",
    "platform": "Interview Cake",
    "type": "practice_problem",
    "title": "The Cashier",
    "description": "Design a cash register that calculates change using the fewest coins.",
    "topics": [],
    "level": "",
    "hours": 0,
    "url": "https://interviewcake.com/the-cashier"
  },
  {
    "id": "interview-cake-1",
    "platform": "Interview Cake",
    "type": "practice_problem",
    "title": "Delete Duplicates from Sorted Array",
    "description": "Remove duplicates from a sorted array in-place.",
    "topics": [],
    "level": "",
    "hours": 0,
    "url": "https://interviewcake.com/delete-duplicates-sorted-array"
  },
  {
    "id": "interview-cake-2",
    "platform": "Interview Cake",
    "type": "practice_problem",
    "title": "Stock Prices",
    "description": "Find the best time to buy and sell a stock given daily prices.",
    "topics": [],
    "level": "",
    "hours": 0,
    "url": "https://interviewcake.com/stock-prices"
  },
  {
    "id": "interview-cake-3",
    "platform": "Interview Cake",
    "type": "practice_problem",
    "title": "Highest Product of 3 Integers",
    "description": "Find three integers whose product is maximum.",
    "topics": [],
    "level": "",
    "hours": 0,
    "url": "https://interviewcake.com/highest-product-of-3-int"
  },
  {
    "id": "interview-cake-4",
    "platform": "Interview Cake",
    "type": "practice_problem",
    "title": "Merge Times",
    "description": "Merge two sorted arrays of meeting times.",
    "topics": [],
    "level": "",
    "hours": 0,
    "url": "https://interviewcake.com/merge-times"
  },
  {
    "id": "interview-cake-5",
    "platform": "Interview Cake",
    "type": "practice_problem",
    "title": "Product of All Integers Except At Index",
    "description": "Compute array product except self without division.",
    "topics": [],
    "level": "",
    "hours": 0,
    "url": "https://interviewcake.com/product-of-all-int-except-at-index"
  },
  {
    "id": "interview-cake-6",
    "platform": "Interview Cake",
    "type": "practice_problem",
    "title": "Largest Continuous Sum",
    "description": "Find largest sum of contiguous subarray.",
    "topics": [],
    "level": "",
    "hours": 0,
    "url": "https://interviewcake.com/largest-continuous-sum"
  },
  {
    "id": "interview-cake-7",
    "platform": "Interview Cake",
    "type": "practice_problem",
    "title": "No Duplicates",
    "description": "Check if array contains all unique values.",
    "topics": [],
    "level": "",
    "hours": 0,
    "url": "https://interviewcake.com/no-duplicates"
  },
  {
    "id": "interview-cake-8",
    "platform": "Interview Cake",
    "type": "practice_problem",
    "title": "Permutation Palindrome",
    "description": "Check if a string can form a palindrome.",
    "topics": [],
    "level": "",
    "hours": 0,
    "url": "https://interviewcake.com/permutation-palindrome"
  },
  {
    "id": "interview-cake-9",
    "platform": "Interview Cake",
    "type": "practice_problem",
    "title": "Word Cloud",
    "description": "Count word frequencies for word cloud generation.",
    "topics": [],
    "level": "",
    "hours": 0,
    "url": "https://interviewcake.com/word-cloud"
  },
  {
    "id": "interview-cake-10",
    "platform": "Interview Cake",
    "type": "practice_problem",
    "title": "Top Characters",
    "description": "Find most frequent characters in a string.",
    "topics": [],
    "level": "",
    "hours": 0,
    "url": "https://interviewcake.com/top-characters"
  },
  {
    "id": "interview-cake-11",
    "platform": "Interview Cake",
    "type": "practice_problem",
    "title": "Balanced Brackets",
    "description": "Check if brackets are balanced using a stack.",
    "topics": [],
    "level": "",
    "hours": 0,
    "url": "https://interviewcake.com/balanced-brackets"
  },
  {
    "id": "interview-cake-12",
    "platform": "Interview Cake",
    "type": "practice_problem",
    "title": "Parentheses",
    "description": "Generate all valid parentheses combinations.",
    "topics": [],
    "level": "",
    "hours": 0,
    "url": "https://interviewcake.com/parentheses"
  },
  {
    "id": "interview-cake-13",
    "platform": "Interview Cake",
    "type": "practice_problem",
    "title": "Apple Trees",
    "description": "Traverse a linked list representing apple trees.",
    "topics": [],
    "level": "",
    "hours": 0,
    "url": "https://interviewcake.com/apple-trees"
  },
  {
    "id": "interview-cake-14",
    "platform": "Interview Cake",
    "type": "practice_problem",
    "title": "Linked List Cycle",
    "description": "Detect cycle in a linked list using Floyd's algorithm.",
    "topics": [],
    "level": "",
    "hours": 0,
    "url": "https://interviewcake.com/linked-list-cycle"
  },
  {
    "id": "interview-cake-15",
    "platform": "Interview Cake",
    "type": "practice_problem",
    "title": "Reverse Linked List",
    "description": "Reverse a singly linked list.",
    "topics": [],
    "level": "",
    "hours": 0,
    "url": "https://interviewcake.com/reverse-linked-list"
  },
  {
    "id": "interview-cake-16",
    "platform": "Interview Cake",
    "type": "practice_problem",
    "title": "Binary Tree Level Order Traversal",
    "description": "Traverse binary tree level by level.",
    "topics": [],
    "level": "",
    "hours": 0,
    "url": "https://interviewcake.com/binary-tree-level-order"
  },
  {
    "id": "interview-cake-17",
    "platform": "Interview Cake",
    "type": "practice_problem",
    "title": "Binary Tree Path Sum",
    "description": "Check if there's a root-to-leaf path summing to target.",
    "topics": [],
    "level": "",
    "hours": 0,
    "url": "https://interviewcake.com/binary-tree-path-sum"
  },
  {
    "id": "interview-cake-18",
    "platform": "Interview Cake",
    "type": "practice_problem",
    "title": "Balanced Binary Tree",
    "description": "Check if binary tree is height-balanced.",
    "topics": [],
    "level": "",
    "hours": 0,
    "url": "https://interviewcake.com/balanced-binary-tree"
  },
  {
    "id": "interview-cake-19",
    "platform": "Interview Cake",
    "type": "practice_problem",
    "title": "Lowest Common Ancestor",
    "description": "Find lowest common ancestor in binary tree.",
    "topics": [],
    "level": "",
    "hours": 0,
    "url": "https://interviewcake.com/lowest-common-ancestor"
  },
  {
    "id": "interview-cake-20",
    "platform": "Interview Cake",
    "type": "practice_problem",
    "title": "Graph Valid Tree",
    "description": "Check if edges form a valid tree (no cycles, connected).",
    "topics": [],
    "level": "",
    "hours": 0,
    "url": "https://interviewcake.com/graph-valid-tree"
  },
  {
    "id": "interview-cake-21",
    "platform": "Interview Cake",
    "type": "practice_problem",
    "title": "Shortest Path Cost",
    "description": "Find shortest path cost in weighted graph.",
    "topics": [],
    "level": "",
    "hours": 0,
    "url": "https://interviewcake.com/shortest-path-cost"
  },
  {
    "id": "interview-cake-22",
    "platform": "Interview Cake",
    "type": "practice_problem",
    "title": "Single Flight Paths",
    "description": "Find if there's exactly one path between cities.",
    "topics": [],
    "level": "",
    "hours": 0,
    "url": "https://interviewcake.com/single-flight-paths"
  },
  {
    "id": "interview-cake-23",
    "platform": "Interview Cake",
    "type": "practice_problem",
    "title": "BFS: Shortest Path",
    "description": "Find shortest path using BFS.",
    "topics": [],
    "level": "",
    "hours": 0,
    "url": "https://interviewcake.com/bfs-shortest-path"
  },
  {
    "id": "interview-cake-24",
    "platform": "Interview Cake",
    "type": "practice_problem",
    "title": "Agent Smith",
    "description": "Find minimum steps for agent replication in grid.",
    "topics": [],
    "level": "",
    "hours": 0,
    "url": "https://interviewcake.com/agent-smith"
  },
  {
    "id": "interview-cake-25",
    "platform": "Interview Cake",
    "type": "practice_problem",
    "title": "Non-overlapping Meeting Rooms",
    "description": "Find minimum meeting rooms needed.",
    "topics": [],
    "level": "",
    "hours": 0,
    "url": "https://interviewcake.com/non-overlapping-meeting-rooms"
  },
  {
    "id": "interview-cake-26",
    "platform": "Interview Cake",
    "type": "practice_problem",
    "title": "Task Scheduler",
    "description": "Schedule tasks with cooldown period.",
    "topics": [],
    "level": "",
    "hours": 0,
    "url": "https://interviewcake.com/task-scheduler"
  },
  {
    "id": "interview-cake-27",
    "platform": "Interview Cake",
    "type": "practice_problem",
    "title": "Missing Numbers",
    "description": "Find missing numbers in two arrays.",
    "topics": [],
    "level": "",
    "hours": 0,
    "url": "https://interviewcake.com/missing-numbers"
  },
  {
    "id": "interview-cake-28",
    "platform": "Interview Cake",
    "type": "practice_problem",
    "title": "Merge Sorted Arrays",
    "description": "Merge two sorted arrays efficiently.",
    "topics": [],
    "level": "",
    "hours": 0,
    "url": "https://interviewcake.com/merge-sorted-arrays"
  },
  {
    "id": "interview-cake-29",
    "platform": "Interview Cake",
    "type": "practice_problem",
    "title": "Search Rotated Sorted Array",
    "description": "Search in rotated sorted array using binary search.",
    "topics": [],
    "level": "",
    "hours": 0,
    "url": "https://interviewcake.com/search-rotated-sorted-array"
  },
  {
    "id": "interview-cake-30",
    "platform": "Interview Cake",
    "type": "practice_problem",
    "title": "K Closest Points to Origin",
    "description": "Find k closest points to origin.",
    "topics": [],
    "level": "",
    "hours": 0,
    "url": "https://interviewcake.com/k-closest-points-origin"
  },
  {
    "id": "interview-cake-31",
    "platform": "Interview Cake",
    "type": "practice_problem",
    "title": "Coin",
    "description": "Minimum coins needed to make change.",
    "topics": [],
    "level": "",
    "hours": 0,
    "url": "https://interviewcake.com/coin"
  },
  {
    "id": "interview-cake-32",
    "platform": "Interview Cake",
    "type": "practice_problem",
    "title": "Robot in a Grid",
    "description": "Find path for robot from top-left to bottom-right.",
    "topics": [],
    "level": "",
    "hours": 0,
    "url": "https://interviewcake.com/robot-in-a-grid"
  },
  {
    "id": "interview-cake-33",
    "platform": "Interview Cake",
    "type": "practice_problem",
    "title": "95th Percentile",
    "description": "Calculate 95th percentile calculator time.",
    "topics": [],
    "level": "",
    "hours": 0,
    "url": "https://interviewcake.com/95th-percentile"
  },
  {
    "id": "interview-cake-34",
    "platform": "Interview Cake",
    "type": "practice_problem",
    "title": "Queue Using Two Stacks",
    "description": "Implement queue using two stacks.",
    "topics": [],
    "level": "",
    "hours": 0,
    "url": "https://interviewcake.com/queue-using-two-stacks"
  },
  {
    "id": "interview-cake-35",
    "platform": "Interview Cake",
    "type": "practice_problem",
    "title": "Stack Queue Animal Shelter",
    "description": "Animal shelter with dequeue by type.",
    "topics": [],
    "level": "",
    "hours": 0,
    "url": "https://interviewcake.com/stack-queue-animal-shelter"
  },
  {
    "id": "interview-cake-36",
    "platform": "Interview Cake",
    "type": "practice_problem",
    "title": "Time to Hire Enough Software Engineers",
    "description": "Find days to hire enough engineers.",
    "topics": [],
    "level": "",
    "hours": 0,
    "url": "https://interviewcake.com/time-to-hire-enough-software-engineers"
  },
  {
    "id": "interview-cake-37",
    "platform": "Interview Cake",
    "type": "practice_problem",
    "title": "Hash Map Cache",
    "description": "Implement LRU cache using hash map and doubly linked list.",
    "topics": [],
    "level": "",
    "hours": 0,
    "url": "https://interviewcake.com/hash-map-cache"
  },
  {
    "id": "interview-cake-38",
    "platform": "Interview Cake",
    "type": "practice_problem",
    "title": "Two Sum",
    "description": "Find two numbers that add up to target.",
    "topics": [],
    "level": "",
    "hours": 0,
    "url": "https://interviewcake.com/two-sum"
  },
  {
    "id": "interview-cake-39",
    "platform": "Interview Cake",
    "type": "practice_problem",
    "title": "Valid Anagram",
    "description": "Check if two strings are anagrams.",
    "topics": [],
    "level": "",
    "hours": 0,
    "url": "https://interviewcake.com/valid-anagram"
  },
  {
    "id": "interview-cake-40",
    "platform": "Interview Cake",
    "type": "practice_problem",
    "title": "Group Anagrams",
    "description": "Group strings that are anagrams.",
    "topics": [],
    "level": "",
    "hours": 0,
    "url": "https://interviewcake.com/group-anagrams"
  },
  {
    "id": "interview-cake-41",
    "platform": "Interview Cake",
    "type": "practice_problem",
    "title": "Longest Substring Without Repeating Characters",
    "description": "Find longest substring without repeating chars.",
    "topics": [],
    "level": "",
    "hours": 0,
    "url": "https://interviewcake.com/longest-substring-without-repeating"
  },
  {
    "id": "interview-cake-42",
    "platform": "Interview Cake",
    "type": "practice_problem",
    "title": "Binary Search",
    "description": "Efficient search algorithm on sorted data.",
    "topics": [],
    "level": "",
    "hours": 0,
    "url": "https://interviewcake.com/binary-search"
  },
  {
    "id": "interview-cake-43",
    "platform": "Interview Cake",
    "type": "practice_problem",
    "title": "Quick Sort",
    "description": "Divide and conquer sorting algorithm.",
    "topics": [],
    "level": "",
    "hours": 0,
    "url": "https://interviewcake.com/quick-sort"
  },
  {
    "id": "interview-cake-44",
    "platform": "Interview Cake",
    "type": "practice_problem",
    "title": "Merge Sort",
    "description": "Stable divide and conquer sorting.",
    "topics": [],
    "level": "",
    "hours": 0,
    "url": "https://interviewcake.com/merge-sort"
  },
  {
    "id": "interview-cake-45",
    "platform": "Interview Cake",
    "type": "practice_problem",
    "title": "Breadth First Search",
    "description": "Level-order graph traversal.",
    "topics": [],
    "level": "",
    "hours": 0,
    "url": "https://interviewcake.com/bfs"
  },
  {
    "id": "interview-cake-46",
    "platform": "Interview Cake",
    "type": "practice_problem",
    "title": "Depth First Search",
    "description": "Recursive graph traversal.",
    "topics": [],
    "level": "",
    "hours": 0,
    "url": "https://interviewcake.com/dfs"
  },
  {
    "id": "interview-cake-47",
    "platform": "Interview Cake",
    "type": "practice_problem",
    "title": "Topological Sort",
    "description": "Linear ordering of directed acyclic graph.",
    "topics": [],
    "level": "",
    "hours": 0,
    "url": "https://interviewcake.com/topological-sort"
  },
  {
    "id": "interview-cake-48",
    "platform": "Interview Cake",
    "type": "practice_problem",
    "title": "Dijkstra's Algorithm",
    "description": "Shortest path in weighted graph with non-negative edges.",
    "topics": [],
    "level": "",
    "hours": 0,
    "url": "https://interviewcake.com/dijkstras-algorithm"
  },
  {
    "id": "interview-cake-49",
    "platform": "Interview Cake",
    "type": "practice_problem",
    "title": "Memoization",
    "description": "Top-down dynamic programming optimization.",
    "topics": [],
    "level": "",
    "hours": 0,
    "url": "https://interviewcake.com/memoization"
  },
  {
    "id": "interview-cake-50",
    "platform": "Interview Cake",
    "type": "practice_problem",
    "title": "Tabulation",
    "description": "Bottom-up dynamic programming.",
    "topics": [],
    "level": "",
    "hours": 0,
    "url": "https://interviewcake.com/tabulation"
  },
  {
    "id": "interview-cake-51",
    "platform": "Interview Cake",
    "type": "practice_problem",
    "title": "Sliding Window",
    "description": "Optimize subarray problems with moving window.",
    "topics": [],
    "level": "",
    "hours": 0,
    "url": "https://interviewcake.com/sliding-window"
  },
  {
    "id": "interview-cake-52",
    "platform": "Interview Cake",
    "type": "practice_problem",
    "title": "Two Pointers",
    "description": "Efficient technique for sorted arrays.",
    "topics": [],
    "level": "",
    "hours": 0,
    "url": "https://interviewcake.com/two-pointers"
  },
  {
    "id": "interview-cake-53",
    "platform": "Interview Cake",
    "type": "practice_problem",
    "title": "Fast and Slow Pointers",
    "description": "Detect cycles and find meetings.",
    "topics": [],
    "level": "",
    "hours": 0,
    "url": "https://interviewcake.com/fast-slow-pointers"
  },
  {
    "id": "interview-cake-54",
    "platform": "Interview Cake",
    "type": "practice_problem",
    "title": "Recursion",
    "description": "Function calling itself with base cases.",
    "topics": [],
    "level": "",
    "hours": 0,
    "url": "https://interviewcake.com/recursion"
  },
  {
    "id": "interview-cake-55",
    "platform": "Interview Cake",
    "type": "practice_problem",
    "title": "Backtracking",
    "description": "Systematic trial and error for constraint satisfaction.",
    "topics": [],
    "level": "",
    "hours": 0,
    "url": "https://interviewcake.com/backtracking"
  },
  {
    "id": "interview-cake-56",
    "platform": "Interview Cake",
    "type": "practice_problem",
    "title": "Bit Manipulation",
    "description": "Efficient operations using binary representations.",
    "topics": [],
    "level": "",
    "hours": 0,
    "url": "https://interviewcake.com/bit-manipulation"
  },
  {
    "id": "interview-cake-57",
    "platform": "Interview Cake",
    "type": "practice_problem",
    "title": "Time and Space Complexity",
    "description": "Big O notation for algorithm analysis.",
    "topics": [],
    "level": "",
    "hours": 0,
    "url": "https://interviewcake.com/time-space-complexity"
  }
]